speedtest_manager/__init__.py
speedtest_manager/client.py
speedtest_manager/connection.py
speedtest_manager/control.py
speedtest_manager/jobs.py
speedtest_manager/logging.py
speedtest_manager/manager.py
speedtest_manager/speedtest.py
speedtest_manager-0.1.12.dist-info/entry_points.txt
speedtest_manager-0.1.12.dist-info/LICENSE
speedtest_manager-0.1.12.dist-info/WHEEL
speedtest_manager-0.1.12.dist-info/METADATA
speedtest_manager-0.1.12.dist-info/RECORD
